simplebot_manga/__init__.py
simplebot_manga/_version.py
simplebot_manga/util.py
simplebot_manga/manga_api/__init__.py
simplebot_manga/manga_api/asurascans.py
simplebot_manga/manga_api/base.py
simplebot_manga/manga_api/heavenmanga.py
simplebot_manga/manga_api/kissmanga.py
simplebot_manga/manga_api/mangabuddy.py
simplebot_manga/manga_api/manganelo.py
simplebot_manga/manga_api/mangatigre.py
simplebot_manga/manga_api/manhuako.py
simplebot_manga/manga_api/ninemanga.py
simplebot_manga/manga_api/tmo.py
simplebot_manga/templates/__init__.py
simplebot_manga/templates/base.j2
simplebot_manga/templates/chapter_list.j2
simplebot_manga/templates/manga_list.j2
simplebot_manga/templates/site_list.j2
simplebot_manga-0.3.0.dist-info/LICENSE
simplebot_manga-0.3.0.dist-info/METADATA
simplebot_manga-0.3.0.dist-info/WHEEL
simplebot_manga-0.3.0.dist-info/entry_points.txt
simplebot_manga-0.3.0.dist-info/top_level.txt
simplebot_manga-0.3.0.dist-info/RECORD
