Metadata-Version: 2.1
Name: simplebot-manga
Version: 0.3.0
Summary: Read manga in Delta Chat (SimpleBot plugin)
Home-page: https://github.com/adbenitez/simplebot_manga
Author: adbenitez
Author-email: adbenitez@nauta.cu
License: MIT
Keywords: simplebot plugin deltachat
Classifier: Development Status :: 4 - Beta
Classifier: Environment :: Plugins
Classifier: Programming Language :: Python :: 3
Classifier: License :: OSI Approved :: MIT License
Classifier: Operating System :: OS Independent
Classifier: Topic :: Utilities
License-File: LICENSE
Requires-Dist: simplebot (>=3.3.0)
Requires-Dist: requests (>=2.28.1)
Requires-Dist: beautifulsoup4 (>=4.11.1)
Requires-Dist: Jinja2 (>=3.1.2)
Requires-Dist: Pillow (>=9.0.1)
Requires-Dist: fpdf2 (>=2.6.0)
Requires-Dist: cachelib (>=0.7.0)
Requires-Dist: json5 (>=0.9.10)
Provides-Extra: dev
Requires-Dist: simplebot (>=3.3.0) ; extra == 'dev'
Requires-Dist: requests (>=2.28.1) ; extra == 'dev'
Requires-Dist: beautifulsoup4 (>=4.11.1) ; extra == 'dev'
Requires-Dist: Jinja2 (>=3.1.2) ; extra == 'dev'
Requires-Dist: Pillow (>=9.0.1) ; extra == 'dev'
Requires-Dist: fpdf2 (>=2.6.0) ; extra == 'dev'
Requires-Dist: cachelib (>=0.7.0) ; extra == 'dev'
Requires-Dist: json5 (>=0.9.10) ; extra == 'dev'
Requires-Dist: pytest (==7.2.0) ; extra == 'dev'
Requires-Dist: black (==22.12.0) ; extra == 'dev'
Requires-Dist: mypy (==0.991) ; extra == 'dev'
Requires-Dist: isort (==5.10.1) ; extra == 'dev'
Requires-Dist: pylint (==2.15.9) ; extra == 'dev'
Requires-Dist: pylama (==8.4.1) ; extra == 'dev'
Requires-Dist: types-requests (==2.28.11.5) ; extra == 'dev'
Provides-Extra: test
Requires-Dist: pytest (==7.2.0) ; extra == 'test'
